partialdispatch-0.1.4.dist-info/METADATA
partialdispatch-0.1.4.dist-info/WHEEL
partialdispatch-0.1.4.dist-info/licenses/LICENSE
partialdispatch/__init__.py
partialdispatch/singledispatch.py
partialdispatch-0.1.4.dist-info/RECORD
