Metadata-Version: 2.1
Name: partialdispatch
Version: 0.1.4
Summary: Function-level logic inspried by functools.singledispatch
Author-Email: Dom Weldon <dom.weldon@gmail.com>
License: MIT
Requires-Python: >=3.8
Provides-Extra: dev
Provides-Extra: test
Provides-Extra: checks
Provides-Extra: ci
Requires-Dist: ruff>=0.0.285; extra == "dev"
Requires-Dist: isort>=5.12.0; extra == "dev"
Requires-Dist: black>=23.7.0; extra == "dev"
Requires-Dist: bandit>=1.7.5; extra == "dev"
Requires-Dist: pytest>=7.4.0; extra == "dev"
Requires-Dist: pytest-cov>=4.1.0; extra == "dev"
Requires-Dist: mypy>=1.5.1; extra == "dev"
Requires-Dist: pytest-custom-exit-code>=0.3.0; extra == "dev"
Requires-Dist: pytest>=7.4.0; extra == "test"
Requires-Dist: pytest-cov>=4.1.0; extra == "test"
Requires-Dist: ruff>=0.0.285; extra == "checks"
Requires-Dist: isort>=5.12.0; extra == "checks"
Requires-Dist: black>=23.7.0; extra == "checks"
Requires-Dist: bandit>=1.7.5; extra == "checks"
Requires-Dist: commitizen>=3.9.0; extra == "ci"
